Metadata-Version: 1.1
Name: typy
Version: 0.0.1
Summary: A light-weight python library to add strongly typed features at runtime (For Python 2.7)
Home-page: https://github.com/201528015329004/TyPy
Author: ray
Author-email: rock307977586@gmail.com
License: UNKNOWN
Download-URL: https://github.com/201528015329004/TyPy/archive/0.2.tar.gz
Keywords: type,strong type,python
Platform: UNKNOWN
